flo_ai/__init__.py
flo_ai/arium/README.md
flo_ai/arium/README_LLM_Router.md
flo_ai/arium/__init__.py
flo_ai/arium/arium.py
flo_ai/arium/base.py
flo_ai/arium/builder.py
flo_ai/arium/events.py
flo_ai/arium/llm_router.py
flo_ai/arium/memory.py
flo_ai/arium/models.py
flo_ai/builder/agent_builder.py
flo_ai/formatter/yaml_format_parser.py
flo_ai/llm/__init__.py
flo_ai/llm/anthropic_llm.py
flo_ai/llm/base_llm.py
flo_ai/llm/gemini_llm.py
flo_ai/llm/ollama_llm.py
flo_ai/llm/openai_llm.py
flo_ai/llm/openai_vllm.py
flo_ai/llm/vertexai_llm.py
flo_ai/models/__init__.py
flo_ai/models/agent.py
flo_ai/models/agent_error.py
flo_ai/models/base_agent.py
flo_ai/models/document.py
flo_ai/models/plan_agents.py
flo_ai/tool/__init__.py
flo_ai/tool/base_tool.py
flo_ai/tool/flo_tool.py
flo_ai/tool/partial_tool.py
flo_ai/tool/plan_tool.py
flo_ai/tool/tool_config.py
flo_ai/utils/__init__.py
flo_ai/utils/document_processor.py
flo_ai/utils/flo_utils.py
flo_ai/utils/logger.py
flo_ai/utils/variable_extractor.py
flo_ai-1.0.6.dist-info/METADATA
flo_ai-1.0.6.dist-info/WHEEL
flo_ai-1.0.6.dist-info/RECORD
