Metadata-Version: 2.3
Name: flo_ai
Version: 1.0.6
Summary: A easy way to create structured AI agents
License: MIT
Author: rootflo
Author-email: *@rootflo.ai
Requires-Python: >=3.10,<4.0
Classifier: License :: OSI Approved :: MIT License
Classifier: Programming Language :: Python :: 3
Classifier: Programming Language :: Python :: 3.10
Classifier: Programming Language :: Python :: 3.11
Classifier: Programming Language :: Python :: 3.12
Classifier: Programming Language :: Python :: 3.13
Provides-Extra: vizualize
Requires-Dist: aiohttp (>=3.12.14,<4.0.0)
Requires-Dist: anthropic (>=0.57.1,<0.58.0)
Requires-Dist: chardet (==3.*)
Requires-Dist: google-cloud-aiplatform (>=1.109.0,<2.0.0)
Requires-Dist: google-genai (>=1.25.0,<2.0.0)
Requires-Dist: httpx (>=0.28.1)
Requires-Dist: matplotlib (>=3.7.0,<4.0.0) ; extra == "vizualize"
Requires-Dist: networkx (>=3.0,<4.0) ; extra == "vizualize"
Requires-Dist: openai (>=1.77.0,<2.0.0)
Requires-Dist: pillow (>=10.3.0,<11.0.0)
Requires-Dist: pydantic (>=2.9.2,<3.0.0)
Requires-Dist: pymupdf4llm (>=0.0.17,<0.0.18)
Requires-Dist: pypdf (>=4.2.0,<5.0.0)
